net_input/__init__.py
net_input/py.typed
net_input/server.py
net_input-1.0.1.dist-info/LICENSE
net_input-1.0.1.dist-info/METADATA
net_input-1.0.1.dist-info/WHEEL
net_input-1.0.1.dist-info/entry_points.txt
net_input-1.0.1.dist-info/top_level.txt
net_input-1.0.1.dist-info/RECORD
