Metadata-Version: 2.1
Name: net-input
Version: 1.0.1
Summary: Send mouse/keyboard inputs via network
Author-email: Pradish Bijukchhe <pradish@sandbox.com.np>
License: Copyright (c) 2018 The Python Packaging Authority
Project-URL: Homepage, https://github.com/sandbox-pokhara/net-input
Project-URL: Issues, https://github.com/sandbox-pokhara/net-input/issues
Classifier: Programming Language :: Python :: 3
Requires-Python: >=3
License-File: LICENSE
Requires-Dist: mouse
Requires-Dist: keyboard
